mcp_deadmansnitch/__init__.py
mcp_deadmansnitch/client.py
mcp_deadmansnitch/server.py
mcp_deadmansnitch-1.0.1.dist-info/METADATA
mcp_deadmansnitch-1.0.1.dist-info/WHEEL
mcp_deadmansnitch-1.0.1.dist-info/entry_points.txt
mcp_deadmansnitch-1.0.1.dist-info/licenses/LICENSE
mcp_deadmansnitch-1.0.1.dist-info/RECORD
