Metadata-Version: 2.4
Name: mcp-deadmansnitch
Version: 1.0.1
Summary: MCP server for Dead Man's Snitch monitoring service
Project-URL: Homepage, https://github.com/jamesbrink/mcp-deadmansnitch
Project-URL: Repository, https://github.com/jamesbrink/mcp-deadmansnitch
Project-URL: Issues, https://github.com/jamesbrink/mcp-deadmansnitch/issues
Project-URL: Documentation, https://github.com/jamesbrink/mcp-deadmansnitch#readme
Author-email: James Brink <james@jamesbrink.net>
Maintainer-email: James Brink <james@jamesbrink.net>
License: MIT
License-File: LICENSE
Keywords: cron,deadmansnitch,mcp,monitoring,scheduled-tasks
Classifier: Development Status :: 4 - Beta
Classifier: Intended Audience :: Developers
Classifier: License :: OSI Approved :: MIT License
Classifier: Programming Language :: Python :: 3
Classifier: Programming Language :: Python :: 3.11
Classifier: Programming Language :: Python :: 3.12
Classifier: Programming Language :: Python :: 3.13
Classifier: Topic :: Software Development :: Libraries :: Python Modules
Classifier: Topic :: System :: Monitoring
Requires-Python: >=3.11
Requires-Dist: fastmcp<3,>=2.14.0
Requires-Dist: httpx>=0.28.1
Requires-Dist: python-dotenv>=1.0.0
